gyat_module/__init__.py
gyatmodule-0.1.1.dist-info/licenses/LICENSE
gyatmodule-0.1.1.dist-info/METADATA
gyatmodule-0.1.1.dist-info/WHEEL
gyatmodule-0.1.1.dist-info/top_level.txt
gyatmodule-0.1.1.dist-info/RECORD
