Metadata-Version: 2.4
Name: gyatModule
Version: 0.1.1
Summary: A sample package that prints text file content
Author: Your Name
Classifier: Programming Language :: Python :: 3
License-File: LICENSE
Dynamic: author
Dynamic: classifier
Dynamic: description
Dynamic: description-content-type
Dynamic: license-file
Dynamic: summary
